systematic_review/__init__.py
systematic_review/analysis.py
systematic_review/citation.py
systematic_review/converter.py
systematic_review/filter_sort.py
systematic_review/nlp.py
systematic_review/os_utils.py
systematic_review/search_count.py
systematic_review/string_manipulation.py
systematic_review/validation.py
systematic_reviewpy_CHANDRAVESH_CHAUDHARI-0.0.2.dist-info/LICENSE.txt
systematic_reviewpy_CHANDRAVESH_CHAUDHARI-0.0.2.dist-info/METADATA
systematic_reviewpy_CHANDRAVESH_CHAUDHARI-0.0.2.dist-info/WHEEL
systematic_reviewpy_CHANDRAVESH_CHAUDHARI-0.0.2.dist-info/top_level.txt
systematic_reviewpy_CHANDRAVESH_CHAUDHARI-0.0.2.dist-info/RECORD
