Metadata-Version: 2.1
Name: systematic-reviewpy-CHANDRAVESH-CHAUDHARI
Version: 0.0.2
Summary: A Python framework for systematic Review.
Home-page: https://github.com/chandraveshchaudhari/systematic-reviewpy
Author: Chandravesh Chaudhari
Author-email: chandraveshchaudhari@gmail.com
Project-URL: Bug Tracker, https://github.com/chandraveshchaudhari/systematic-reviewpy/issues
Project-URL: Bug Reports, https://github.com/chandraveshchaudhari/systematic-reviewpy/issues
Project-URL: Say Thanks!, https://saythanks.io/to/chandraveshchaudhari
Project-URL: Source, https://github.com/chandraveshchaudhari/systematic-reviewpy/
Keywords: browser,automation,systematic review,research papers,Bibliometric analysis
Classifier: Development Status :: 3 - Alpha
Classifier: Operating System :: OS Independent
Classifier: Intended Audience :: Science/Research
Classifier: Intended Audience :: End Users/Desktop
Classifier: Topic :: Software Development :: Build Tools
Classifier: Topic :: Internet :: WWW/HTTP :: Browsers
Classifier: License :: OSI Approved :: MIT License
Classifier: Programming Language :: Python :: 3.8
Requires-Python: >=3.8
License-File: LICENSE.txt
Requires-Dist: pandas
Requires-Dist: rispy
Requires-Dist: matplotlib
Requires-Dist: seaborn
